k8s_monitor/__init__.py
k8s_monitor/autoscaling_policy.py
k8s_monitor/cli.py
k8s_monitor/config.py
k8s_monitor/metrics.py
k8s_monitor/mock_k8s.py
k8s_monitor/monitor.py
k8s_monitor/namespace_config.py
k8s_monitor/visualize.py
k8s_monitor/storage/__init__.py
k8s_monitor/storage/database.py
k8s_monitor/utils/__init__.py
k8s_monitor/utils/email_alerts.py
k8s_monitor/utils/email_config.py
k8s_resource_monitor-0.1.0.dist-info/LICENSE
k8s_resource_monitor-0.1.0.dist-info/METADATA
k8s_resource_monitor-0.1.0.dist-info/WHEEL
k8s_resource_monitor-0.1.0.dist-info/entry_points.txt
k8s_resource_monitor-0.1.0.dist-info/top_level.txt
k8s_resource_monitor-0.1.0.dist-info/RECORD
