Metadata-Version: 2.1
Name: k8s-resource-monitor
Version: 0.1.0
Summary: A CLI tool for monitoring Kubernetes resources and autoscaling
Home-page: https://github.com/shramish2057/k8s_resource_monitor.git
Author: Shramish Kafle
Author-email: shramish4@gmail.com
Classifier: Programming Language :: Python :: 3
Classifier: License :: OSI Approved :: MIT License
Classifier: Operating System :: OS Independent
Requires-Python: >=3.6
License-File: LICENSE
Requires-Dist: click
Requires-Dist: rich
Requires-Dist: kubernetes
Requires-Dist: matplotlib
Requires-Dist: requests
